{
  "uuid": "de55aa33-38b6-4acd-aa11-792963db75d8",
  "shortName": "carwings",
  "longName": "Pebble Carwings",
  "companyName": "Philip Cali",
  "versionCode": 1,
  "versionLabel": "0.1",
  "capabilities": [
    "configurable",
    "location"
  ],
  "watchapp": {
    "watchface": false
  },
  "appKeys": {},
  "resources": {
    "media": [
      {
        "type": "png",
        "name": "IMAGE_MENU_ABOUT",
        "file": "images/about.png"
      },
      {
        "type": "png",
        "name": "IMAGE_MENU_INFO",
        "file": "images/info.png"
      },
      {
        "type": "png",
        "name": "IMAGE_MENU_AC_OFF",
        "file": "images/fan.png"
      },
      {
        "type": "png",
        "name": "IMAGE_MENU_AC_ON",
        "file": "images/moving_fan.png"
      },
      {
        "type": "png",
        "name": "IMAGE_MENU_REFRESH",
        "file": "images/refresh.png"
      },
      {
        "type": "png",
        "name": "IMAGE_MENU_LOCATION",
        "file": "images/location.png"
      },
      {
        "type": "png",
        "name": "IMAGE_LOGO_SPLASH",
        "file": "images/logo_splash.png"
      },
      {
        "type": "png",
        "name": "IMAGE_TILE_SPLASH",
        "file": "images/tile_splash.png"
      },
      {
        "type": "font",
        "name": "MONO_FONT_14",
        "file": "fonts/UbuntuMono-Regular.ttf"
      }
    ]
  },
  "targetPlatforms": [
    "aplite",
    "basalt"
  ],
  "sdkVersion": "3"
}
